Metadata-Version: 1.1
Name: randomio2
Version: 0.1
Summary: attr: randomio.__doc__
Home-page: https://github.com/ZuluPro/random-io
Author: Anthony Monthe (ZuluPro)
Author-email: anthony.monthe@gmail.com
License: UNKNOWN
Keywords: file,test,random
Platform: UNKNOWN
Classifier: Development Status :: 4 - Beta
Classifier: Environment :: Console
Classifier: Intended Audience :: Developers
Classifier: Intended Audience :: System Administrators
Classifier: License :: OSI Approved :: BSD License
Classifier: Operating System :: OS Independent
Classifier: Programming Language :: Python
Classifier: Programming Language :: Python :: 3
Classifier: Topic :: Software Development
Classifier: Topic :: Software Development :: Build Tools
Classifier: Topic :: Software Development :: Libraries :: Python Modules
Classifier: Topic :: Software Development :: Testing
Classifier: Topic :: System :: Archiving :: Packaging
